covid19forecast/cases.py
covid19forecast/forecast.py
covid19forecast-1.1.0.dist-info/LICENSE
covid19forecast-1.1.0.dist-info/METADATA
covid19forecast-1.1.0.dist-info/WHEEL
covid19forecast-1.1.0.dist-info/top_level.txt
covid19forecast-1.1.0.dist-info/RECORD
