Metadata-Version: 2.1
Name: covid19forecast
Version: 1.1.0
Summary: Python Package to get Covid19  Forecasting For all Cases Every Country in future using FBProphet Model
Home-page: https://iraqprogrammer.wordpress.com/
Author: Falah.G.Saleh
Author-email: falahgs07@gmail.com
License: UNKNOWN
Keywords: Covid19,CoronaVirus,Forecasting
Platform: UNKNOWN
Classifier: Programming Language :: Python :: 3
Classifier: Programming Language :: Python :: 3.5
Classifier: Programming Language :: Python :: 3.6
Classifier: Programming Language :: Python :: 3.7
Classifier: Programming Language :: Python :: 3.8
Classifier: License :: OSI Approved :: MIT License
Classifier: Operating System :: OS Independent
Requires-Python: >=3.6
Requires-Dist: fbprophet
Requires-Dist: pandas
Requires-Dist: matplotlib
